{
  "add": "追加",
  "create": "作成",
  "save": "保存",
  "continue": "続ける",
  "remove": "削除",
  "key": "キー",
  "value": "値",
  "next": "次へ",
  "back": "戻る",
  "export": "エクスポート",
  "action": "アクション",
  "download": "ダウンロード",
  "clear": "クリア",
  "on": "オン",
  "off": "オフ",
  "edit": "編集",
  "enabled": "有効",
  "disabled": "無効",
  "disable": "無効",
  "none": "none",
  "signOut": "サインアウト",
  "manageAccount": "アカウントの管理",
  "serverInfo": "サーバー情報",
  "testConnection": "接続テスト",
  "description": "説明",
  "type": "タイプ",
  "category": "カテゴリー",
  "priority": "優先度",
  "clientScope": {
    "default": "DEFAULT"
  },
  "allTypes": "すべてのタイプ",
  "manage": "管理",
  "clients": "クライアント",
  "clientScopes": "クライアント・スコープ",
  "realmRoles": "レルムロール",
  "users": "ユーザー",
  "sessions": "セッション",
  "events": "イベント",
  "mappers": "マッパー",
  "configure": "設定",
  "realmSettings": "レルムの設定",
  "authentication": "認証",
  "identityProviders": "アイデンティティー・プロバイダー",
  "userFederation": "ユーザー・フェデレーション",
  "settings": "設定",
  "details": "詳細",
  "Sunday": "日",
  "Monday": "月",
  "Tuesday": "火",
  "Wednesday": "水",
  "Thursday": "木",
  "Friday": "金",
  "Saturday": "土",
  "times": {
    "seconds": "秒",
    "minutes": "分",
    "hours": "時",
    "days": "日"
  },
  "attributes": "属性",
  "credentials": "クレデンシャル",
  "clientId": "クライアントID",
  "id": "ID",
  "mapperType": "マッパータイプ",
  "leave": "外す",
  "password": "パスワード",
  "passwordConfirmation": "新しいパスワード（確認）",
  "temporaryPassword": "一時的",
  "temporaryPasswordHelpText": "有効の場合は、ユーザーは次のログイン時にパスワードの変更が必要となります。"
}